{
  "is_error":0,
  "version":3,
  "count":1,
  "id":58541,
  "values":{
    "58541":{
      "id":58541,
      "contact_type":"Individual",
      "contact_sub_type":"null",
      "do_not_email":null,
      "do_not_phone":null,
      "do_not_mail":null,
      "do_not_sms":null,
      "do_not_trade":null,
      "is_opt_out":null,
      "legal_identifier":null,
      "external_identifier":null,
      "sort_name":"Teh, Adrian",
      "display_name":"Adrian Teh",
      "nick_name":null,
      "legal_name":null,
      "image_URL":null,
      "preferred_communication_method":null,
      "preferred_language":"en_US",
      "preferred_mail_format":null,
      "hash":"47ba6c0ed01b060281598d232fda714e",
      "api_key":null,
      "first_name":"Adrian",
      "middle_name":null,
      "last_name":"Teh",
      "prefix_id":null,
      "suffix_id":null,
      "email_greeting_id":"1",
      "email_greeting_custom":null,
      "email_greeting_display":null,
      "postal_greeting_id":"1",
      "postal_greeting_custom":null,
      "postal_greeting_display":null,
      "addressee_id":"1",
      "addressee_custom":null,
      "addressee_display":null,
      "job_title":null,
      "gender_id":null,
      "birth_date":null,
      "is_deceased":null,
      "deceased_date":null,
      "household_name":null,
      "primary_contact_id":null,
      "organization_name":null,
      "sic_code":null,
      "user_unique_id":null
    }
  }
}